{
  "report_version": "1.1",
  "started_at": "2026-04-08T21:51:21.956406",
  "duration_ms": 0.0,
  "iterations": 80,
  "success_count": 0,
  "failed_count": 0,
  "metrics": {},
  "summary": {},
  "quality": {},
  "tuning": {},
  "gate": {
    "status": "SKIP",
    "quality_level": "none",
    "failed_rules": [],
    "warn_rules": [
      {
        "rule": "dependency",
        "detail": "pandas unavailable: No module named 'pandas'",
        "level": "warn"
      }
    ]
  },
  "error": "pandas not available: No module named 'pandas'"
}